napistu/__init__.py
napistu/__main__.py
napistu/_cli.py
napistu/consensus.py
napistu/constants.py
napistu/identifiers.py
napistu/indices.py
napistu/sbml_dfs_core.py
napistu/sbml_dfs_utils.py
napistu/source.py
napistu/context/__init__.py
napistu/context/discretize.py
napistu/context/filtering.py
napistu/gcs/__init__.py
napistu/gcs/assets.py
napistu/gcs/constants.py
napistu/gcs/downloads.py
napistu/gcs/utils.py
napistu/genomics/__init__.py
napistu/genomics/constants.py
napistu/genomics/gsea.py
napistu/genomics/scverse_loading.py
napistu/ingestion/__init__.py
napistu/ingestion/bigg.py
napistu/ingestion/constants.py
napistu/ingestion/gtex.py
napistu/ingestion/harmonizome.py
napistu/ingestion/hpa.py
napistu/ingestion/idea_yeast.py
napistu/ingestion/identifiers_etl.py
napistu/ingestion/intact.py
napistu/ingestion/napistu_edgelist.py
napistu/ingestion/obo.py
napistu/ingestion/omnipath.py
napistu/ingestion/organismal_species.py
napistu/ingestion/perturbseq.py
napistu/ingestion/psi_mi.py
napistu/ingestion/reactome.py
napistu/ingestion/reactome_fi.py
napistu/ingestion/sbml.py
napistu/ingestion/string.py
napistu/ingestion/trrust.py
napistu/matching/__init__.py
napistu/matching/constants.py
napistu/matching/interactions.py
napistu/matching/mount.py
napistu/matching/species.py
napistu/mcp/__init__.py
napistu/mcp/__main__.py
napistu/mcp/chat_web.py
napistu/mcp/cli_utils.py
napistu/mcp/client.py
napistu/mcp/codebase.py
napistu/mcp/codebase_utils.py
napistu/mcp/component_base.py
napistu/mcp/config.py
napistu/mcp/constants.py
napistu/mcp/documentation.py
napistu/mcp/documentation_utils.py
napistu/mcp/execution.py
napistu/mcp/health.py
napistu/mcp/inspect_utils.py
napistu/mcp/profiles.py
napistu/mcp/semantic_search.py
napistu/mcp/semantic_search_utils.py
napistu/mcp/server.py
napistu/mcp/tutorials.py
napistu/mcp/tutorials_utils.py
napistu/mcp/utils.py
napistu/mcp/web_routes.py
napistu/modify/__init__.py
napistu/modify/cofactors.py
napistu/modify/constants.py
napistu-0.9.0.dist-info/licenses/LICENSE
napistu-0.9.0.dist-info/METADATA
napistu-0.9.0.dist-info/WHEEL
napistu-0.9.0.dist-info/entry_points.txt
napistu-0.9.0.dist-info/top_level.txt
napistu-0.9.0.dist-info/RECORD
