Metadata-Version: 2.4
Name: napistu
Version: 0.9.0
Summary: Connecting high-dimensional data to curated pathways
Home-page: https://github.com/napistu/napistu-py
Author: Sean Hackett
Author-email: seanmchackett@gmail.com
Project-URL: Documentation, https://napistu.readthedocs.io
Project-URL: Source, https://github.com/napistu/napistu-py
Project-URL: Tracker, https://github.com/napistu/napistu-py/issues
Classifier: License :: OSI Approved :: MIT License
Classifier: Operating System :: OS Independent
Classifier: Programming Language :: Python :: 3
Classifier: Programming Language :: Python :: 3 :: Only
Requires-Python: >=3.11
License-File: LICENSE
Requires-Dist: beautifulsoup4<5.0.0,>=4.11.0
Requires-Dist: click<9.0.0,>=8.0.0
Requires-Dist: rich>=13.0.0
Requires-Dist: fs<3.0.0,>=2.4.16
Requires-Dist: fs-gcsfs<2.0.0,>=1.5.0
Requires-Dist: igraph
Requires-Dist: Jinja2
Requires-Dist: matplotlib<4.0.0,>=3.5.0
Requires-Dist: mygene<4.0.0,>=3.0.0
Requires-Dist: numpy<3.0.0,>=1.24.0
Requires-Dist: pandas<3.0.0,>=1.5.0
Requires-Dist: pyarrow<20.0.0,>=15.0.0
Requires-Dist: pydantic<3.0.0,>=2.0.0
Requires-Dist: python-libsbml
Requires-Dist: PyYAML<7.0.0,>=6.0.0
Requires-Dist: omnipath
Requires-Dist: requests>=2.25.0
Requires-Dist: scipy<2.0.0,>=1.10.0
Requires-Dist: tqdm
Requires-Dist: zeep<4.0.0,>=3.0.0
Provides-Extra: dev
Requires-Dist: napistu[genomics,mcp]; extra == "dev"
Requires-Dist: black>=26.0.0; extra == "dev"
Requires-Dist: ipykernel; extra == "dev"
Requires-Dist: pre-commit<4.0.0,>=3.0.0; extra == "dev"
Requires-Dist: pytest<8.0.0,>=7.0.0; extra == "dev"
Requires-Dist: pytest-asyncio; extra == "dev"
Requires-Dist: pytest-cov; extra == "dev"
Requires-Dist: ruff; extra == "dev"
Requires-Dist: testcontainers; extra == "dev"
Provides-Extra: mcp
Requires-Dist: anthropic<1.0,>=0.73.0; extra == "mcp"
Requires-Dist: chromadb<1.0.0,>=0.4.15; extra == "mcp"
Requires-Dist: fastmcp<3.0.0,>=2.13.0; extra == "mcp"
Requires-Dist: httpx>=0.24.0; extra == "mcp"
Requires-Dist: jupyter-client>=7.0.0; extra == "mcp"
Requires-Dist: markdown>=3.4.0; extra == "mcp"
Requires-Dist: mcp<2.0.0,>=1.0.0; extra == "mcp"
Requires-Dist: nbformat>=5.0.0; extra == "mcp"
Requires-Dist: sentence-transformers<3.0.0,>=2.2.0; extra == "mcp"
Provides-Extra: rpy2
Requires-Dist: rpy2<4.0.0,>=3.5.0; extra == "rpy2"
Requires-Dist: rpy2-arrow<1.0.0,>=0.1.0; extra == "rpy2"
Provides-Extra: genomics
Requires-Dist: anndata; extra == "genomics"
Requires-Dist: gseapy; extra == "genomics"
Requires-Dist: mudata; extra == "genomics"
Requires-Dist: statsmodels; extra == "genomics"
Dynamic: license-file
